LICENSE
MANIFEST.in
README.rst
setup.cfg
setup.py
django_wellknown_security.egg-info/PKG-INFO
django_wellknown_security.egg-info/SOURCES.txt
django_wellknown_security.egg-info/dependency_links.txt
django_wellknown_security.egg-info/top_level.txt
docs/Makefile
docs/conf.py
docs/index.rst
docs/make.bat
wellknown_security/__init__.py
wellknown_security/admin.py
wellknown_security/apps.py
wellknown_security/models.py
wellknown_security/tests.py
wellknown_security/urls.py
wellknown_security/views.py
wellknown_security/migrations/__init__.py